tcs_protowhat/Feedback.py
tcs_protowhat/Reporter.py
tcs_protowhat/State.py
tcs_protowhat/Test.py
tcs_protowhat/__init__.py
tcs_protowhat/failure.py
tcs_protowhat/sct_context.py
tcs_protowhat/sct_syntax.py
tcs_protowhat/selectors.py
tcs_protowhat/utils.py
tcs_protowhat/utils_ast.py
tcs_protowhat/utils_messaging.py
tcs_protowhat/checks/__init__.py
tcs_protowhat/checks/check_bash_history.py
tcs_protowhat/checks/check_files.py
tcs_protowhat/checks/check_funcs.py
tcs_protowhat/checks/check_logic.py
tcs_protowhat/checks/check_simple.py
tcsprotowhat/Feedback.py
tcsprotowhat/Reporter.py
tcsprotowhat/State.py
tcsprotowhat/Test.py
tcsprotowhat/__init__.py
tcsprotowhat/failure.py
tcsprotowhat/sct_context.py
tcsprotowhat/sct_syntax.py
tcsprotowhat/selectors.py
tcsprotowhat/utils.py
tcsprotowhat/utils_ast.py
tcsprotowhat/utils_messaging.py
tcsprotowhat/checks/__init__.py
tcsprotowhat/checks/check_bash_history.py
tcsprotowhat/checks/check_files.py
tcsprotowhat/checks/check_funcs.py
tcsprotowhat/checks/check_logic.py
tcsprotowhat/checks/check_simple.py
tcsprotowhat-2.1.0.dist-info/LICENSE
tcsprotowhat-2.1.0.dist-info/METADATA
tcsprotowhat-2.1.0.dist-info/WHEEL
tcsprotowhat-2.1.0.dist-info/top_level.txt
tcsprotowhat-2.1.0.dist-info/RECORD
